odoo/addons/delivery_tnt_oca/README.rst
odoo/addons/delivery_tnt_oca/__init__.py
odoo/addons/delivery_tnt_oca/__manifest__.py
odoo/addons/delivery_tnt_oca/data/product_packaging_data.xml
odoo/addons/delivery_tnt_oca/doc/ExpressConnect/ExpressConnect Pricing Integration Guide v3 Schema.pdf
odoo/addons/delivery_tnt_oca/doc/ExpressConnect/ExpressConnect Shipping Integration Guide v3.pdf
odoo/addons/delivery_tnt_oca/doc/ExpressConnect/ExpressConnect_Tracking_V3_1.pdf
odoo/addons/delivery_tnt_oca/doc/ExpressLabel/ExpressLabel Integration Guide v1.10.pdf
odoo/addons/delivery_tnt_oca/doc/ExpressLabel/ExpressLabel_Integration Guide_Arrangements.pdf
odoo/addons/delivery_tnt_oca/i18n/delivery_tnt_oca.pot
odoo/addons/delivery_tnt_oca/i18n/es.po
odoo/addons/delivery_tnt_oca/models/__init__.py
odoo/addons/delivery_tnt_oca/models/delivery_carrier.py
odoo/addons/delivery_tnt_oca/models/product_packaging.py
odoo/addons/delivery_tnt_oca/models/stock_picking.py
odoo/addons/delivery_tnt_oca/models/tnt_request.py
odoo/addons/delivery_tnt_oca/readme/CONFIGURE.rst
odoo/addons/delivery_tnt_oca/readme/CONTRIBUTORS.rst
odoo/addons/delivery_tnt_oca/readme/DESCRIPTION.rst
odoo/addons/delivery_tnt_oca/readme/ROADMAP.rst
odoo/addons/delivery_tnt_oca/readme/USAGE.rst
odoo/addons/delivery_tnt_oca/report/picking_templates.xml
odoo/addons/delivery_tnt_oca/report/stock_report_views.xml
odoo/addons/delivery_tnt_oca/static/description/icon.png
odoo/addons/delivery_tnt_oca/static/description/index.html
odoo/addons/delivery_tnt_oca/tests/__init__.py
odoo/addons/delivery_tnt_oca/tests/test_delivery_tnt.py
odoo/addons/delivery_tnt_oca/views/delivery_carrier_view.xml
odoo14_addon_delivery_tnt_oca-14.0.1.2.5.dist-info/METADATA
odoo14_addon_delivery_tnt_oca-14.0.1.2.5.dist-info/WHEEL
odoo14_addon_delivery_tnt_oca-14.0.1.2.5.dist-info/top_level.txt
odoo14_addon_delivery_tnt_oca-14.0.1.2.5.dist-info/RECORD
