Metadata-Version: 2.1
Name: odoo14-addon-delivery-tnt-oca
Version: 14.0.1.2.5
Summary: Integrate TNT webservice
Home-page: https://github.com/OCA/delivery-carrier
Author: Tecnativa, Odoo Community Association (OCA)
Author-email: support@odoo-community.org
License: AGPL-3
Platform: UNKNOWN
Classifier: Programming Language :: Python
Classifier: Framework :: Odoo
Classifier: Framework :: Odoo :: 14.0
Classifier: License :: OSI Approved :: GNU Affero General Public License v3
Requires-Python: >=3.6
Requires-Dist: dicttoxml
Requires-Dist: odoo14-addon-delivery-package-number
Requires-Dist: odoo14-addon-delivery-state
Requires-Dist: odoo14-addon-product-dimension
Requires-Dist: odoo <14.1dev,>=14.0a
Requires-Dist: xmltodict
